[

 {
   "model": "user_profile.city",
   "pk": 1,
   "fields": {
     "name": "Madison",
		"state": 49
	}
 },


 {
   "model": "user_profile.city",
   "pk": 2,
   "fields": {
     "name": "Minneapolis",
		"state": 23
	}
 },

 {
   "model": "user_profile.city",
   "pk": 3,
   "fields": {
     "name": "Green Bay",
		"state": 49
	}
 },

{
   "model": "user_profile.city",
   "pk": 4,
   "fields": {
     "name": "Milwaukee",
		"state": 49
	}
 },

 {
   "model": "user_profile.city",
   "pk": 5,
   "fields": {
     "name": "Duluth",
		"state": 23
	}
 },

 {
   "model": "user_profile.city",
   "pk": 6,
   "fields": {
     "name": "Chicago",
		"state": 13
	}
 },
 {
   "model": "user_profile.city",
   "pk": 7,
   "fields": {
     "name": "Birmingham",
		"state": 1
	}
 },
 {
   "model": "user_profile.city",
   "pk": 8,
   "fields": {
     "name": "Huntsville",
		"state": 1
	}
 },
 {
   "model": "user_profile.city",
   "pk": 9,
   "fields": {
     "name": "Mobile",
		"state": 1
	}
 },
 {
   "model": "user_profile.city",
   "pk": 10,
   "fields": {
     "name": "Montgomery",
		"state": 1
	}
 },
 {
   "model": "user_profile.city",
   "pk": 11,
   "fields": {
     "name": "Anchorage",
		"state": 2
	}
 },
 {
   "model": "user_profile.city",
   "pk": 12,
   "fields": {
     "name": "Phoenix",
		"state": 3
	}
 },
 {
   "model": "user_profile.city",
   "pk": 13,
   "fields": {
     "name": "Tucson",
		"state": 3
	}
 },
 {
   "model": "user_profile.city",
   "pk": 14,
   "fields": {
     "name": "Mesa",
		"state": 3
	}
 },
 {
   "model": "user_profile.city",
   "pk": 15,
   "fields": {
     "name": "Chandler",
		"state": 3
	}
 },
 {
   "model": "user_profile.city",
   "pk": 16,
   "fields": {
     "name": "Glendale",
		"state": 3
	}
 },
 {
   "model": "user_profile.city",
   "pk": 17,
   "fields": {
     "name": "Scottsdale",
		"state": 3
	}
 },
 {
   "model": "user_profile.city",
   "pk": 18,
   "fields": {
     "name": "Little Rock",
		"state": 4
	}
 },
 {
   "model": "user_profile.city",
   "pk": 19,
   "fields": {
     "name": "Fayatteville",
		"state": 4
	}
 },
 {
   "model": "user_profile.city",
   "pk": 20,
   "fields": {
     "name": "Fort Smith",
		"state": 4
	}
 },
 {
   "model": "user_profile.city",
   "pk": 21,
   "fields": {
     "name": "Los Angeles",
		"state": 5
	}
 },
 {
   "model": "user_profile.city",
   "pk": 22,
   "fields": {
     "name": "San Francisco",
		"state": 5
	}
 },
 {
   "model": "user_profile.city",
   "pk": 23,
   "fields": {
     "name": "San Diego",
		"state": 5
	}
 },
 {
   "model": "user_profile.city",
   "pk": 24,
   "fields": {
     "name": "Riverside",
		"state": 5
	}
 },
 {
   "model": "user_profile.city",
   "pk": 25,
   "fields": {
     "name": "Sacramento",
		"state": 5
	}
 },
 {
   "model": "user_profile.city",
   "pk": 26,
   "fields": {
     "name": "San Jose",
		"state": 5
	}
 },
 {
   "model": "user_profile.city",
   "pk": 27,
   "fields": {
     "name": "Fresno",
		"state": 5
	}
 },
 {
   "model": "user_profile.city",
   "pk": 28,
   "fields": {
     "name": "Concord",
		"state": 5
	}
 },
 {
   "model": "user_profile.city",
   "pk": 29,
   "fields": {
     "name": "San Clemente",
		"state": 5
	}
 },
 {
   "model": "user_profile.city",
   "pk": 30,
   "fields": {
     "name": "Bakersfield",
		"state": 5
	}
 },
 {
   "model": "user_profile.city",
   "pk": 31,
   "fields": {
     "name": "Murrieta",
		"state": 5
	}
 },
 {
   "model": "user_profile.city",
   "pk": 32,
   "fields": {
     "name": "Stockton",
		"state": 5
	}
 },
 {
   "model": "user_profile.city",
   "pk": 33,
   "fields": {
     "name": "Oxnard",
		"state": 5
	}
 },
 {
   "model": "user_profile.city",
   "pk": 34,
   "fields": {
     "name": "Modesto",
		"state": 5
	}
 },
 {
   "model": "user_profile.city",
   "pk": 35,
   "fields": {
     "name": "Denver",
		"state": 6
	}
 },
 {
   "model": "user_profile.city",
   "pk": 36,
   "fields": {
     "name": "Boulder",
		"state": 6
	}
 },
 {
   "model": "user_profile.city",
   "pk": 37,
   "fields": {
     "name": "Colorado Springs",
		"state": 6
	}
 },
 {
   "model": "user_profile.city",
   "pk": 38,
   "fields": {
     "name": "Greeley",
		"state": 6
	}
 },
 {
   "model": "user_profile.city",
   "pk": 39,
   "fields": {
     "name": "Fort Collins",
		"state": 6
	}
 },
 {
   "model": "user_profile.city",
   "pk": 40,
   "fields": {
     "name": "Bridgeport",
		"state": 7
	}
 },
 {
   "model": "user_profile.city",
   "pk": 41,
   "fields": {
     "name": "New Haven",
		"state": 7
	}
 },
 {
   "model": "user_profile.city",
   "pk": 42,
   "fields": {
     "name": "Hartford",
		"state": 7
	}
 },
 {
   "model": "user_profile.city",
   "pk": 43,
   "fields": {
     "name": "Waterbury",
		"state": 7
	}
 },
 {
   "model": "user_profile.city",
   "pk": 44,
   "fields": {
     "name": "Wilmington",
		"state": 8
	}
 },
 {
   "model": "user_profile.city",
   "pk": 45,
   "fields": {
     "name": "Georgetown",
		"state": 8
	}
 },
 {
   "model": "user_profile.city",
   "pk": 46,
   "fields": {
     "name": "Miami",
		"state": 9
	}
 },
 {
   "model": "user_profile.city",
   "pk": 47,
   "fields": {
     "name": "Orlando",
		"state": 9
	}
 },
 {
   "model": "user_profile.city",
   "pk": 48,
   "fields": {
     "name": "Jacksonville",
		"state": 9
	}
 },
 {
   "model": "user_profile.city",
   "pk": 49,
   "fields": {
     "name": "Tampa",
		"state": 9
	}
 },
 {
   "model": "user_profile.city",
   "pk": 50,
   "fields": {
     "name": "Fort Myers",
		"state": 9
	}
 },
 {
   "model": "user_profile.city",
   "pk": 51,
   "fields": {
     "name": "Pensacola",
		"state": 9
	}
 },
 {
   "model": "user_profile.city",
   "pk": 52,
   "fields": {
     "name": "Atlanta",
		"state": 10
	}
 },
 {
   "model": "user_profile.city",
   "pk": 53,
   "fields": {
     "name": "Augusta",
		"state": 10
	}
 },
 {
   "model": "user_profile.city",
   "pk": 54,
   "fields": {
     "name": "Savannah",
		"state": 10
	}
 },
 {
   "model": "user_profile.city",
   "pk": 55,
   "fields": {
     "name": "Honolulu",
		"state": 11
	}
 },
 {
   "model": "user_profile.city",
   "pk": 56,
   "fields": {
     "name": "Boise",
		"state": 12
	}
 },
 {
   "model": "user_profile.city",
   "pk": 57,
   "fields": {
     "name": "Chicago",
		"state": 13
	}
 },
 {
   "model": "user_profile.city",
   "pk": 58,
   "fields": {
     "name": "Rockford",
		"state": 13
	}
 },
 {
   "model": "user_profile.city",
   "pk": 59,
   "fields": {
     "name": "Peoria",
		"state": 13
	}
 },
 {
   "model": "user_profile.city",
   "pk": 60,
   "fields": {
     "name": "Champaign",
		"state": 13
	}
 },
 {
   "model": "user_profile.city",
   "pk": 61,
   "fields": {
     "name": "Indianapolis",
		"state": 14
	}
 },
 {
   "model": "user_profile.city",
   "pk": 62,
   "fields": {
     "name": "Fort Wayne",
		"state": 14
	}
 },
 {
   "model": "user_profile.city",
   "pk": 63,
   "fields": {
     "name": "Des Moines",
		"state": 15
	}
 },
 {
   "model": "user_profile.city",
   "pk": 64,
   "fields": {
     "name": "Cedar Rapids",
		"state": 15
	}
 },
 {
   "model": "user_profile.city",
   "pk": 65,
   "fields": {
     "name": "Witchita",
		"state": 16
	}
 },
 {
   "model": "user_profile.city",
   "pk": 66,
   "fields": {
     "name": "Topeka",
		"state": 16
	}
 },
 {
   "model": "user_profile.city",
   "pk": 67,
   "fields": {
     "name": "Louisville",
		"state": 17
	}
 },
 {
   "model": "user_profile.city",
   "pk": 68,
   "fields": {
     "name": "Lexington",
		"state": 17
	}
 },
 {
   "model": "user_profile.city",
   "pk": 69,
   "fields": {
     "name": "New Orleans",
		"state": 18
	}
 },
 {
   "model": "user_profile.city",
   "pk": 70,
   "fields": {
     "name": "Baton Rouge",
		"state": 18
	}
 },
 {
   "model": "user_profile.city",
   "pk": 71,
   "fields": {
     "name": "Lafayette",
		"state": 18
	}
 },
 {
   "model": "user_profile.city",
   "pk": 72,
   "fields": {
     "name": "Shreveport",
		"state": 18
	}
 },
 {
   "model": "user_profile.city",
   "pk": 73,
   "fields": {
     "name": "Portland",
		"state": 19
	}
 },
 {
   "model": "user_profile.city",
   "pk": 74,
   "fields": {
     "name": "Baltimore",
		"state": 20
	}
 },
 {
   "model": "user_profile.city",
   "pk": 75,
   "fields": {
     "name": "Boston",
		"state": 21
	}
 },
 {
   "model": "user_profile.city",
   "pk": 76,
   "fields": {
     "name": "Worcester",
		"state": 21
	}
 },
 {
   "model": "user_profile.city",
   "pk": 77,
   "fields": {
     "name": "Detroit",
		"state": 22
	}
 },
 {
   "model": "user_profile.city",
   "pk": 78,
   "fields": {
     "name": "Flint",
		"state": 22
	}
 },
 {
   "model": "user_profile.city",
   "pk": 79,
   "fields": {
     "name": "Ann Arbor",
		"state": 22
	}
 },
 {
   "model": "user_profile.city",
   "pk": 80,
   "fields": {
     "name": "Grand Rapids",
		"state": 22
	}
 },
 {
   "model": "user_profile.city",
   "pk": 81,
   "fields": {
     "name": "Kalamazoo",
		"state": 22
	}
 },
 {
   "model": "user_profile.city",
   "pk": 82,
   "fields": {
     "name": "Saginaw",
		"state": 22
	}
 },
 {
   "model": "user_profile.city",
   "pk": 83,
   "fields": {
     "name": "Jackson",
		"state": 24
	}
 },
 {
   "model": "user_profile.city",
   "pk": 84,
   "fields": {
     "name": "Gulfport",
		"state": 24
	}
 },
 {
   "model": "user_profile.city",
   "pk": 85,
   "fields": {
     "name": "St. Louis",
		"state": 25
	}
 },
 {
   "model": "user_profile.city",
   "pk": 86,
   "fields": {
     "name": "Kansas City",
		"state": 25
	}
 },
 {
   "model": "user_profile.city",
   "pk": 87,
   "fields": {
     "name": "Springfield",
		"state": 25
	}
 },
 {
   "model": "user_profile.city",
   "pk": 88,
   "fields": {
     "name": "Billings",
		"state": 26
	}
 },
 {
   "model": "user_profile.city",
   "pk": 89,
   "fields": {
     "name": "Omaha",
		"state": 27
	}
 },
 {
   "model": "user_profile.city",
   "pk": 90,
   "fields": {
     "name": "Lincoln",
		"state": 27
	}
 },
 {
   "model": "user_profile.city",
   "pk": 91,
   "fields": {
     "name": "Las Vegas",
		"state": 28
	}
 },
 {
   "model": "user_profile.city",
   "pk": 92,
   "fields": {
     "name": "Reno",
		"state": 28
	}
 },
 {
   "model": "user_profile.city",
   "pk": 93,
   "fields": {
     "name": "Manchester",
		"state": 29
	}
 },
 {
   "model": "user_profile.city",
   "pk": 94,
   "fields": {
     "name": "Lebanon",
		"state": 29
	}
 },
 {
   "model": "user_profile.city",
   "pk": 95,
   "fields": {
     "name": "Newark",
		"state": 30
	}
 },
 {
   "model": "user_profile.city",
   "pk": 96,
   "fields": {
     "name": "Atlantic City",
		"state": 30
	}
 },
{
   "model": "user_profile.city",
   "pk": 97,
   "fields": {
     "name": "Trenton",
		"state": 30
	}
 },
 {
   "model": "user_profile.city",
   "pk": 98,
   "fields": {
     "name": "Albuquerque",
		"state": 31
	}
 },
 {
   "model": "user_profile.city",
   "pk": 99,
   "fields": {
     "name": "New York",
		"state": 32
	}
 },
{
   "model": "user_profile.city",
   "pk": 100,
   "fields": {
     "name": "Buffalo",
		"state": 32
	}
 },
{
   "model": "user_profile.city",
   "pk": 101,
   "fields": {
     "name": "Albany",
		"state": 32
	}
 },
{
   "model": "user_profile.city",
   "pk": 102,
   "fields": {
     "name": "Syracuse",
		"state": 32
	}
 },
{
   "model": "user_profile.city",
   "pk": 103,
   "fields": {
     "name": "Rochester",
		"state": 32
	}
 },
{
   "model": "user_profile.city",
   "pk": 104,
   "fields": {
     "name": "Charlotte",
		"state": 33
	}
 },
{
   "model": "user_profile.city",
   "pk": 105,
   "fields": {
     "name": "Raleigh",
		"state": 33
	}
 },
{
   "model": "user_profile.city",
   "pk": 106,
   "fields": {
     "name": "Greensboro",
		"state": 33
	}
 },
{
   "model": "user_profile.city",
   "pk": 107,
   "fields": {
     "name": "Winston-Salem",
		"state": 33
	}
 },
{
   "model": "user_profile.city",
   "pk": 108,
   "fields": {
     "name": "Fargo",
		"state": 34
	}
 },
{
   "model": "user_profile.city",
   "pk": 109,
   "fields": {
     "name": "Cleveland",
		"state": 35
	}
 },
{
   "model": "user_profile.city",
   "pk": 110,
   "fields": {
     "name": "Akron",
		"state": 35
	}
 },
{
   "model": "user_profile.city",
   "pk": 111,
   "fields": {
     "name": "Columbus",
		"state": 35
	}
 },
{
   "model": "user_profile.city",
   "pk": 112,
   "fields": {
     "name": "Cincinnati",
		"state": 35
	}
 },
{
   "model": "user_profile.city",
   "pk": 113,
   "fields": {
     "name": "Dayton",
		"state": 35
	}
 },
{
   "model": "user_profile.city",
   "pk": 114,
   "fields": {
     "name": "Toledo",
		"state": 35
	}
 },
{
   "model": "user_profile.city",
   "pk": 115,
   "fields": {
     "name": "Youngstown",
		"state": 35
	}
 },
{
   "model": "user_profile.city",
   "pk": 116,
   "fields": {
     "name": "Canton",
		"state": 35
	}
 },
{
   "model": "user_profile.city",
   "pk": 117,
   "fields": {
     "name": "Oklahoma City",
		"state": 36
	}
 },
{
   "model": "user_profile.city",
   "pk": 118,
   "fields": {
     "name": "Tulsa",
		"state": 36
	}
 },
{
   "model": "user_profile.city",
   "pk": 119,
   "fields": {
     "name": "Portland",
		"state": 37
	}
 },
{
   "model": "user_profile.city",
   "pk": 120,
   "fields": {
     "name": "Salem",
		"state": 37
	}
 },
{
   "model": "user_profile.city",
   "pk": 121,
   "fields": {
     "name": "Eugene",
		"state": 37
	}
 },
{
   "model": "user_profile.city",
   "pk": 122,
   "fields": {
     "name": "Philadelphia",
		"state": 38
	}
 },
{
   "model": "user_profile.city",
   "pk": 123,
   "fields": {
     "name": "Pittsburgh",
		"state": 38
	}
 },
{
   "model": "user_profile.city",
   "pk": 124,
   "fields": {
     "name": "Reading",
		"state": 38
	}
 },
{
   "model": "user_profile.city",
   "pk": 125,
   "fields": {
     "name": "Allentown",
		"state": 38
	}
 },
{
   "model": "user_profile.city",
   "pk": 126,
   "fields": {
     "name": "Harrisburg",
		"state": 38
	}
 },
{
   "model": "user_profile.city",
   "pk": 127,
   "fields": {
     "name": "Scranton",
		"state": 38
	}
 },
{
   "model": "user_profile.city",
   "pk": 128,
   "fields": {
     "name": "York",
		"state": 38
	}
 },
{
   "model": "user_profile.city",
   "pk": 129,
   "fields": {
     "name": "Lancaster",
		"state": 38
	}
 },
{
   "model": "user_profile.city",
   "pk": 130,
   "fields": {
     "name": "Erie",
		"state": 38
	}
 },
{
   "model": "user_profile.city",
   "pk": 131,
   "fields": {
     "name": "Providence",
		"state": 39
	}
 },
{
   "model": "user_profile.city",
   "pk": 132,
   "fields": {
     "name": "Greenville",
		"state": 40
	}
 },
{
   "model": "user_profile.city",
   "pk": 133,
   "fields": {
     "name": "Columbia",
		"state": 40
	}
 },
{
   "model": "user_profile.city",
   "pk": 134,
   "fields": {
     "name": "Charleston",
		"state": 40
	}
 },
{
   "model": "user_profile.city",
   "pk": 135,
   "fields": {
     "name": "Myrtle Beach",
		"state": 40
	}
 },
{
   "model": "user_profile.city",
   "pk": 136,
   "fields": {
     "name": "Sioux Falls",
		"state": 41
	}
 },
{
   "model": "user_profile.city",
   "pk": 137,
   "fields": {
     "name": "Nashville",
		"state": 42
	}
 },
{
   "model": "user_profile.city",
   "pk": 138,
   "fields": {
     "name": "Knoxville",
		"state": 42
	}
 },
{
   "model": "user_profile.city",
   "pk": 139,
   "fields": {
     "name": "Erie",
		"state": 42
	}
 },
{
   "model": "user_profile.city",
   "pk": 140,
   "fields": {
     "name": "Memphis",
		"state": 42
	}
 },
{
   "model": "user_profile.city",
   "pk": 141,
   "fields": {
     "name": "Chattanooga",
		"state": 42
	}
 },
{
   "model": "user_profile.city",
   "pk": 142,
   "fields": {
     "name": "Johnson City",
		"state": 42
	}
 },
{
   "model": "user_profile.city",
   "pk": 143,
   "fields": {
     "name": "Dallas",
		"state": 43
	}
 },
{
   "model": "user_profile.city",
   "pk": 144,
   "fields": {
     "name": "Fort Worth",
		"state": 43
	}
 },
{
   "model": "user_profile.city",
   "pk": 145,
   "fields": {
     "name": "Houston",
		"state": 43
	}
 },
{
   "model": "user_profile.city",
   "pk": 146,
   "fields": {
     "name": "San Antonio",
		"state": 43
	}
 },
{
   "model": "user_profile.city",
   "pk": 147,
   "fields": {
     "name": "Austin",
		"state": 43
	}
 },
{
   "model": "user_profile.city",
   "pk": 148,
   "fields": {
     "name": "El Paso",
		"state": 43
	}
 },
{
   "model": "user_profile.city",
   "pk": 149,
   "fields": {
     "name": "McAllen",
		"state": 43
	}
 },
{
   "model": "user_profile.city",
   "pk": 150,
   "fields": {
     "name": "Corpus Christi",
		"state": 43
	}
 },
{
   "model": "user_profile.city",
   "pk": 151,
   "fields": {
     "name": "Beaumont",
		"state": 43
	}
 },
{
   "model": "user_profile.city",
   "pk": 152,
   "fields": {
     "name": "Killeen",
		"state": 43
	}
 },
{
   "model": "user_profile.city",
   "pk": 153,
   "fields": {
     "name": "Lubbock",
		"state": 43
	}
 },
{
   "model": "user_profile.city",
   "pk": 154,
   "fields": {
     "name": "Salt Lake City",
		"state": 44
	}
 },
{
   "model": "user_profile.city",
   "pk": 155,
   "fields": {
     "name": "Ogden",
		"state": 44
	}
 },
{
   "model": "user_profile.city",
   "pk": 156,
   "fields": {
     "name": "Provo",
		"state": 44
	}
 },
{
   "model": "user_profile.city",
   "pk": 157,
   "fields": {
     "name": "Burlington",
		"state": 45
	}
 },
{
   "model": "user_profile.city",
   "pk": 158,
   "fields": {
     "name": "Norfolk",
		"state": 46
	}
 },
{
   "model": "user_profile.city",
   "pk": 159,
   "fields": {
     "name": "Richmond",
		"state": 46
	}
 },
{
   "model": "user_profile.city",
   "pk": 160,
   "fields": {
     "name": "Roanoke",
		"state": 46
	}
 },
{
   "model": "user_profile.city",
   "pk": 161,
   "fields": {
     "name": "Lynchburg",
		"state": 46
	}
 },
{
   "model": "user_profile.city",
   "pk": 162,
   "fields": {
     "name": "Seattle",
		"state": 47
	}
 },
{
   "model": "user_profile.city",
   "pk": 163,
   "fields": {
     "name": "Spokane",
		"state": 47
	}
 },
{
   "model": "user_profile.city",
   "pk": 164,
   "fields": {
     "name": "Olympia",
		"state": 47
	}
 },
{
   "model": "user_profile.city",
   "pk": 165,
   "fields": {
     "name": "Kennewick",
		"state": 47
	}
 },
{
   "model": "user_profile.city",
   "pk": 166,
   "fields": {
     "name": "Bremerton",
		"state": 47
	}
 },
{
   "model": "user_profile.city",
   "pk": 167,
   "fields": {
     "name": "Charleston",
		"state": 48
	}
 },
{
   "model": "user_profile.city",
   "pk": 168,
   "fields": {
     "name": "Huntington",
		"state": 48
	}
 },
{
   "model": "user_profile.city",
   "pk": 169,
   "fields": {
     "name": "Appleton",
		"state": 49
	}
 },
{
   "model": "user_profile.city",
   "pk": 170,
   "fields": {
     "name": "Eau Claire",
		"state": 49
	}
 },
{
   "model": "user_profile.city",
   "pk": 171,
   "fields": {
     "name": "Cheyenne",
		"state": 50
	}
 },
{
   "model": "user_profile.city",
   "pk": 172,
   "fields": {
     "name": "Jackson",
		"state": 50
	}
 },
{
   "model": "user_profile.city",
   "pk": 173,
   "fields": {
     "name": "Washington",
		"state": 51
	}
 }
]